__init__.py
performance_tracing.py
timer.py
clodo_py_tools-0.0.1.dist-info/METADATA
clodo_py_tools-0.0.1.dist-info/WHEEL
clodo_py_tools-0.0.1.dist-info/entry_points.txt
clodo_py_tools-0.0.1.dist-info/top_level.txt
clodo_py_tools-0.0.1.dist-info/RECORD
